osnap_lib/__init__.py
osnap_lib-0.1.0.dist-info/LICENSE
osnap_lib-0.1.0.dist-info/METADATA
osnap_lib-0.1.0.dist-info/WHEEL
osnap_lib-0.1.0.dist-info/top_level.txt
osnap_lib-0.1.0.dist-info/RECORD
