Metadata-Version: 2.1
Name: osnap-lib
Version: 0.1.0
Summary: OSNAP library for implementing OSNAP Agents
Home-page: https://github.com/yourusername/osnap-lib
Author: Shreyas Kulkarni
Author-email: sk@simplyfi.ai
License: UNKNOWN
Platform: UNKNOWN
Classifier: Development Status :: 3 - Alpha
Classifier: Intended Audience :: Developers
Classifier: License :: OSI Approved :: MIT License
Classifier: Programming Language :: Python :: 3
Classifier: Programming Language :: Python :: 3.6
Classifier: Programming Language :: Python :: 3.7
Classifier: Programming Language :: Python :: 3.8
Classifier: Programming Language :: Python :: 3.9
Requires-Python: >=3.6
License-File: LICENSE
Requires-Dist: rsa
